<!-- Illuminant data from: https://github.com/colour-science/colour/blob/develop/colour/colorimetry/datasets/illuminants/sds.py -->
<scene version="3.0.0">
	<shape type="rectangle" id="emit-light" name="emit-light">
		<boolean name="flip_normals" value="true"/>
		<transform name="to_world">
			<matrix value="0.000001 0.000000 -0.500000 -41.366695 0.000001 7.480000 0.000000 19.882002 7.480000 -0.000001 0.000000 20.304798 0.000000 0.000000 0.000000 1.000000"/>
		</transform>
		<emitter type="area" name="emitter">
			<!-- <rgb value="7.068584 7.068584 7.068584" name="radiance"/> -->
			<spectrum name="radiance" value="380:0.67, 385:0.84, 390:1.06, 395:1.24, 400:1.47, 405:8.72, 410:2.41, 415:2.23, 420:2.50, 425:2.77, 430:3.02, 435:19.70, 440:3.52, 445:3.73, 450:3.93, 455:4.11, 460:4.26, 465:4.38, 470:4.46, 475:4.51, 480:4.52, 485:4.49, 490:4.49, 495:4.40, 500:4.34, 505:4.22, 510:4.11, 515:4.01, 520:3.95, 525:3.94, 530:4.00, 535:4.12, 540:4.32, 545:13.71, 550:4.90, 555:5.21, 560:5.50, 565:5.74, 570:5.90, 575:7.18, 580:7.29, 585:5.76, 590:5.50, 595:5.20, 600:4.82, 605:4.42, 610:4.00, 615:3.59, 620:3.20, 625:2.83, 630:2.48, 635:2.18, 640:1.90, 645:1.66, 650:1.45, 655:1.26, 660:1.10, 665:0.97, 670:0.85, 675:0.75, 680:0.66, 685:0.59, 690:0.58, 695:0.47, 700:0.43, 705:0.39, 710:0.37, 715:0.32, 720:0.30, 725:0.28, 730:0.26, 735:0.24, 740:0.22, 745:0.21, 750:0.20, 755:0.18, 760:0.54, 765:0.16, 770:0.20, 775:0.15, 780:0.14" />
		</emitter>
		<bsdf type="null" name="bsdf"/>
	</shape>
	<shape type="rectangle" id="emit-light0" name="emit-light0">
		<boolean name="flip_normals" value="true"/>
		<transform name="to_world">
			<matrix value="12.179999 0.000000 0.000000 2.126528 0.000000 0.000000 0.500000 62.946301 0.000000 -12.180000 0.000000 21.397684 0.000000 0.000000 0.000000 1.000000"/>
		</transform>
		<emitter type="area" name="emitter">
			<!-- <rgb value="4.712389 4.712389 4.712389" name="radiance"/> -->
			<spectrum name="radiance" value="380:0.45, 385:0.56, 390:0.70, 395:0.82, 400:0.98, 405:5.82, 410:1.60, 415:1.49, 420:1.67, 425:1.85, 430:2.02, 435:13.13, 440:2.34, 445:2.49, 450:2.62, 455:2.74, 460:2.84, 465:2.92, 470:2.98, 475:3.01, 480:3.01, 485:2.99, 490:2.99, 495:2.93, 500:2.89, 505:2.81, 510:2.74, 515:2.67, 520:2.64, 525:2.63, 530:2.67, 535:2.74, 540:2.88, 545:9.14, 550:3.26, 555:3.47, 560:3.66, 565:3.83, 570:3.93, 575:4.79, 580:4.86, 585:3.84, 590:3.67, 595:3.47, 600:3.21, 605:2.95, 610:2.67, 615:2.40, 620:2.13, 625:1.89, 630:1.66, 635:1.45, 640:1.26, 645:1.11, 650:0.97, 655:0.84, 660:0.73, 665:0.64, 670:0.57, 675:0.50, 680:0.44, 685:0.39, 690:0.39, 695:0.32, 700:0.28, 705:0.26, 710:0.25, 715:0.22, 720:0.20, 725:0.18, 730:0.17, 735:0.16, 740:0.15, 745:0.14, 750:0.13, 755:0.12, 760:0.36, 765:0.11, 770:0.14, 775:0.10, 780:0.09" />
		</emitter>
		<bsdf type="null" name="bsdf"/>
	</shape>
	<shape type="rectangle" id="emit-light1" name="emit-light1">
		<boolean name="flip_normals" value="true"/>
		<transform name="to_world">
			<matrix value="12.179999 0.000000 0.000000 31.588627 0.000000 0.000000 0.500000 62.946301 0.000000 -12.180000 0.000000 20.535725 0.000000 0.000000 0.000000 1.000000"/>
		</transform>
		<emitter type="area" name="emitter">
			<!-- <rgb value="4.712389 4.712389 4.712389" name="radiance"/> -->
			<spectrum name="radiance" value="380:0.45, 385:0.56, 390:0.70, 395:0.82, 400:0.98, 405:5.82, 410:1.60, 415:1.49, 420:1.67, 425:1.85, 430:2.02, 435:13.13, 440:2.34, 445:2.49, 450:2.62, 455:2.74, 460:2.84, 465:2.92, 470:2.98, 475:3.01, 480:3.01, 485:2.99, 490:2.99, 495:2.93, 500:2.89, 505:2.81, 510:2.74, 515:2.67, 520:2.64, 525:2.63, 530:2.67, 535:2.74, 540:2.88, 545:9.14, 550:3.26, 555:3.47, 560:3.66, 565:3.83, 570:3.93, 575:4.79, 580:4.86, 585:3.84, 590:3.67, 595:3.47, 600:3.21, 605:2.95, 610:2.67, 615:2.40, 620:2.13, 625:1.89, 630:1.66, 635:1.45, 640:1.26, 645:1.11, 650:0.97, 655:0.84, 660:0.73, 665:0.64, 670:0.57, 675:0.50, 680:0.44, 685:0.39, 690:0.39, 695:0.32, 700:0.28, 705:0.26, 710:0.25, 715:0.22, 720:0.20, 725:0.18, 730:0.17, 735:0.16, 740:0.15, 745:0.14, 750:0.13, 755:0.12, 760:0.36, 765:0.11, 770:0.14, 775:0.10, 780:0.09" />
		</emitter>
		<bsdf type="null" name="bsdf"/>
	</shape>
	<shape type="rectangle" id="emit-light2" name="emit-light2">
		<boolean name="flip_normals" value="true"/>
		<transform name="to_world">
			<matrix value="12.179999 0.000000 0.000000 1.264569 0.000000 0.000000 0.500000 62.946301 0.000000 -12.180000 0.000000 -8.064415 0.000000 0.000000 0.000000 1.000000"/>
		</transform>
		<emitter type="area" name="emitter">
			<!-- <rgb value="4.712389 4.712389 4.712389" name="radiance"/> -->
			<spectrum name="radiance" value="380:0.45, 385:0.56, 390:0.70, 395:0.82, 400:0.98, 405:5.82, 410:1.60, 415:1.49, 420:1.67, 425:1.85, 430:2.02, 435:13.13, 440:2.34, 445:2.49, 450:2.62, 455:2.74, 460:2.84, 465:2.92, 470:2.98, 475:3.01, 480:3.01, 485:2.99, 490:2.99, 495:2.93, 500:2.89, 505:2.81, 510:2.74, 515:2.67, 520:2.64, 525:2.63, 530:2.67, 535:2.74, 540:2.88, 545:9.14, 550:3.26, 555:3.47, 560:3.66, 565:3.83, 570:3.93, 575:4.79, 580:4.86, 585:3.84, 590:3.67, 595:3.47, 600:3.21, 605:2.95, 610:2.67, 615:2.40, 620:2.13, 625:1.89, 630:1.66, 635:1.45, 640:1.26, 645:1.11, 650:0.97, 655:0.84, 660:0.73, 665:0.64, 670:0.57, 675:0.50, 680:0.44, 685:0.39, 690:0.39, 695:0.32, 700:0.28, 705:0.26, 710:0.25, 715:0.22, 720:0.20, 725:0.18, 730:0.17, 735:0.16, 740:0.15, 745:0.14, 750:0.13, 755:0.12, 760:0.36, 765:0.11, 770:0.14, 775:0.10, 780:0.09" />
		</emitter>
		<bsdf type="null" name="bsdf"/>
	</shape>
	<shape type="rectangle" id="emit-light3" name="emit-light3">
		<boolean name="flip_normals" value="true"/>
		<transform name="to_world">
			<matrix value="12.179999 0.000000 0.000000 30.726669 0.000000 0.000000 0.500000 62.946301 0.000000 -12.180000 0.000000 -8.926374 0.000000 0.000000 0.000000 1.000000"/>
		</transform>
		<emitter type="area" name="emitter">
			<!-- <rgb value="4.712389 4.712389 4.712389" name="radiance"/> -->
			<spectrum name="radiance" value="380:0.45, 385:0.56, 390:0.70, 395:0.82, 400:0.98, 405:5.82, 410:1.60, 415:1.49, 420:1.67, 425:1.85, 430:2.02, 435:13.13, 440:2.34, 445:2.49, 450:2.62, 455:2.74, 460:2.84, 465:2.92, 470:2.98, 475:3.01, 480:3.01, 485:2.99, 490:2.99, 495:2.93, 500:2.89, 505:2.81, 510:2.74, 515:2.67, 520:2.64, 525:2.63, 530:2.67, 535:2.74, 540:2.88, 545:9.14, 550:3.26, 555:3.47, 560:3.66, 565:3.83, 570:3.93, 575:4.79, 580:4.86, 585:3.84, 590:3.67, 595:3.47, 600:3.21, 605:2.95, 610:2.67, 615:2.40, 620:2.13, 625:1.89, 630:1.66, 635:1.45, 640:1.26, 645:1.11, 650:0.97, 655:0.84, 660:0.73, 665:0.64, 670:0.57, 675:0.50, 680:0.44, 685:0.39, 690:0.39, 695:0.32, 700:0.28, 705:0.26, 710:0.25, 715:0.22, 720:0.20, 725:0.18, 730:0.17, 735:0.16, 740:0.15, 745:0.14, 750:0.13, 755:0.12, 760:0.36, 765:0.11, 770:0.14, 775:0.10, 780:0.09" />
		</emitter>
		<bsdf type="null" name="bsdf"/>
	</shape>
</scene>
